ETIA/__init__.py
ETIA/AFS/AFS.py
ETIA/AFS/__init__.py
ETIA/AFS/feature_selector.py
ETIA/AFS/oos.py
ETIA/AFS/predictive_configurator.py
ETIA/AFS/predictive_model.py
ETIA/AFS/preprocessor.py
ETIA/AFS/feature_selectors/__init__.py
ETIA/AFS/feature_selectors/fbed_with_idx.R
ETIA/AFS/feature_selectors/ses_with_idx.R
ETIA/AFS/jsons/fs_algs.json
ETIA/AFS/jsons/pred_algs.json
ETIA/AFS/jsons/preprocess_algs.json
ETIA/AFS/utils/__init__.py
ETIA/CRV/__init__.py
ETIA/CRV/adjustment/__init__.py
ETIA/CRV/adjustment/adjset_R.py
ETIA/CRV/adjustment/function_find_adjset_daggity.py
ETIA/CRV/adjustment/run_adjset_dagitty_r.R
ETIA/CRV/adjustment/run_adjset_pcalg_r.R
ETIA/CRV/causal_graph_utils/__init__.py
ETIA/CRV/causal_graph_utils/bidirected_path.py
ETIA/CRV/causal_graph_utils/confidence_causal_findings.py
ETIA/CRV/causal_graph_utils/cpdag_to_dag.py
ETIA/CRV/causal_graph_utils/create_sub_mag_pag.py
ETIA/CRV/causal_graph_utils/dag_to_cpdag.py
ETIA/CRV/causal_graph_utils/dag_to_mag_removeL.py
ETIA/CRV/causal_graph_utils/data_functions.py
ETIA/CRV/causal_graph_utils/enforce_stationarity.py
ETIA/CRV/causal_graph_utils/find_ancestors_nx.py
ETIA/CRV/causal_graph_utils/get_unshielded_triples.py
ETIA/CRV/causal_graph_utils/has_inducing_path_dag.py
ETIA/CRV/causal_graph_utils/is_collider.py
ETIA/CRV/causal_graph_utils/is_dag.py
ETIA/CRV/causal_graph_utils/mag_to_pag.py
ETIA/CRV/causal_graph_utils/markov_boundary.py
ETIA/CRV/causal_graph_utils/one_bidirected_path.py
ETIA/CRV/causal_graph_utils/one_directed_path.py
ETIA/CRV/causal_graph_utils/one_path_anytype.py
ETIA/CRV/causal_graph_utils/one_potentially_directed_path.py
ETIA/CRV/causal_graph_utils/orientation_rules.py
ETIA/CRV/causal_graph_utils/orientation_rules_cpdag.py
ETIA/CRV/causal_graph_utils/pag_to_mag.py
ETIA/CRV/confidence/__init__.py
ETIA/CRV/confidence/confidence.py
ETIA/CRV/queries/__init__.py
ETIA/CRV/queries/one_bidirected_path.py
ETIA/CRV/queries/one_directed_path.py
ETIA/CRV/queries/one_path_anytype.py
ETIA-1.0.3.dist-info/METADATA
ETIA-1.0.3.dist-info/WHEEL
ETIA-1.0.3.dist-info/top_level.txt
ETIA-1.0.3.dist-info/RECORD
