Metadata-Version: 2.1
Name: ETIA
Version: 1.0.3
Summary: Automated Causal Discovery Library
Home-page: https://github.com/mensxmachina/ETIA
Author-email: droubo@csd.uoc.gr
Requires-Dist: causalnex
Requires-Dist: cdt
Requires-Dist: joblib
Requires-Dist: jpype1
Requires-Dist: networkx>=3.2.1
Requires-Dist: numpy
Requires-Dist: pandas
Requires-Dist: pgmpy
Requires-Dist: py4cytoscape
Requires-Dist: pywhy-graphs
Requires-Dist: scikit-learn
Requires-Dist: tigramite>=5.2.3.1
Requires-Dist: matplotlib
Requires-Dist: dcor
